LICENSE.txt
MANIFEST.in
PKGINFO.rst
setup.py
brainfuck/Base.py
brainfuck/Brainfuck.py
brainfuck/Nice.py
brainfuck/Trolls.py
brainfuck/__init__.py
brainfuck.egg-info/PKG-INFO
brainfuck.egg-info/SOURCES.txt
brainfuck.egg-info/dependency_links.txt
brainfuck.egg-info/top_level.txt