Metadata-Version: 1.1
Name: brainfuck
Version: 1.0.2
Summary: Epic Brainfuck Interpreter
Home-page: https://github.com/gfyoung/brainfuck
Author: G. Young
Author-email: None - use the home-page instead!
License: MIT License
Download-URL: https://github.com/gfyoung/brainfuck
Keywords: brainfuck interpreter epic console
Platform: UNKNOWN
Classifier: Environment :: Console
Classifier: Intended Audience :: Developers
Classifier: Intended Audience :: End Users/Desktop
Classifier: License :: OSI Approved :: MIT License
Classifier: Programming Language :: Python
Classifier: Natural Language :: English
Classifier: Topic :: Software Development :: Interpreters
